LICENSE
MANIFEST.in
README.rst
setup.cfg
setup.py
homeassistant/.DS_Store
homeassistant/__init__.py
homeassistant/__main__.py
homeassistant/bootstrap.py
homeassistant/config.py
homeassistant/const.py
homeassistant/core.py
homeassistant/exceptions.py
homeassistant/loader.py
homeassistant/remote.py
homeassistant/components/.DS_Store
homeassistant/components/__init__.py
homeassistant/components/alexa.py
homeassistant/components/apcupsd.py
homeassistant/components/api.py
homeassistant/components/arduino.py
homeassistant/components/bloomsky.py
homeassistant/components/browser.py
homeassistant/components/configurator.py
homeassistant/components/conversation.py
homeassistant/components/demo.py
homeassistant/components/device_sun_light_trigger.py
homeassistant/components/digital_ocean.py
homeassistant/components/discovery.py
homeassistant/components/downloader.py
homeassistant/components/dweet.py
homeassistant/components/ecobee.py
homeassistant/components/emulated_hue.py
homeassistant/components/enocean.py
homeassistant/components/envisalink.py
homeassistant/components/feedreader.py
homeassistant/components/ffmpeg.py
homeassistant/components/foursquare.py
homeassistant/components/graphite.py
homeassistant/components/group.py
homeassistant/components/hdmi_cec.py
homeassistant/components/history.py
homeassistant/components/homematic.py
homeassistant/components/http.py
homeassistant/components/ifttt.py
homeassistant/components/influxdb.py
homeassistant/components/input_boolean.py
homeassistant/components/input_select.py
homeassistant/components/input_slider.py
homeassistant/components/insteon_hub.py
homeassistant/components/introduction.py
homeassistant/components/isy994.py
homeassistant/components/joaoapps_join.py
homeassistant/components/keyboard.py
homeassistant/components/keyboard_remote.py
homeassistant/components/knx.py
homeassistant/components/lirc.py
homeassistant/components/logbook.py
homeassistant/components/logentries.py
homeassistant/components/logger.py
torvy_hass.egg-info/PKG-INFO
torvy_hass.egg-info/SOURCES.txt
torvy_hass.egg-info/dependency_links.txt
torvy_hass.egg-info/entry_points.txt
torvy_hass.egg-info/not-zip-safe
torvy_hass.egg-info/requires.txt
torvy_hass.egg-info/top_level.txt