Metadata-Version: 1.1
Name: torvy-hass
Version: 0.1
Summary: Open-source home automation platform running on Python 3.
Home-page: http://smarttorvy.me/
Author: Smart Torvy Team
Author-email: hello@smarttorvy.me
License: MIT License
Download-URL: https://github.com/smart-torvy/torvy-home-assistant/archive/0.1.zip
Keywords: home,automation
Platform: any
Classifier: Intended Audience :: End Users/Desktop
Classifier: Intended Audience :: Developers
Classifier: License :: OSI Approved :: MIT License
Classifier: Operating System :: OS Independent
Classifier: Programming Language :: Python :: 3.4
Classifier: Topic :: Home Automation
